Cerebro/__init__.py
Cerebro/test.py
Cerebro/image/FaceTracking.py
Cerebro/image/__init__.py
Cerebro/image/feature_extraction.py
Cerebro/image/utils.py
Cerebro/image/enhancement/__init__.py
Cerebro/image/enhancement/alignment.py
Cerebro/image/enhancement/filters.py
Cerebro/image/face_detector/__cascade_face_detector.py
Cerebro/image/face_detector/__init__.py
Cerebro/image/face_detector/detect_dlib.py
Cerebro/image/face_detector/detect_haar.py
Cerebro/image/face_detector/detect_lbp.py
Cerebro/interface/__init__.py
Cerebro/interface/process_image.py
Cerebro/interface/process_video.py
Cerebro/interface/video_stream.py
Cerebro/model/__init__.py
Cerebro/model/controller.py
Cerebro/model/emotions_model.py
Cerebro/saved-models/__init__.py
CEREBRO8-0.0.1.dist-info/LICENSE
CEREBRO8-0.0.1.dist-info/METADATA
CEREBRO8-0.0.1.dist-info/WHEEL
CEREBRO8-0.0.1.dist-info/top_level.txt
CEREBRO8-0.0.1.dist-info/RECORD
