Metadata-Version: 2.1
Name: CEREBRO8
Version: 0.0.1
Summary: Recognizing facial expressions from images, videos and real-time stream
Home-page: https://github.com/AmrSaber/Cerebro
Author: AmrSaber, WafaaIsmail, MohamedAhmed, SalmaSayed, MuhammadAref, ManarArabi
Author-email: amr.m.saber.mail@gmail.com, wafaaismail595@gmail.com, mohamedmaim97@gmail.com, Salmasayed797@gmail.com, muhammad.aref224@gmail.com, manar.araby.ma@gmail.com
License: gpl-3.0
Download-URL: https://github.com/AmrSaber/Cerebro/archive/v1.0.tar.gz
Keywords: emotions,expressions,real-time stream
Platform: UNKNOWN
Classifier: Development Status :: 5 - Production/Stable
Classifier: Intended Audience :: Developers
Classifier: Intended Audience :: Education
Classifier: License :: OSI Approved :: GNU Affero General Public License v3
Classifier: Operating System :: Microsoft :: Windows
Classifier: Operating System :: POSIX :: Linux
Classifier: Programming Language :: Python :: 3.6
Requires-Dist: opencv-contrib-python (==3.4.4.19)
Requires-Dist: numpy
Requires-Dist: moviepy
Requires-Dist: ffmpeg-python
Requires-Dist: imutils
Requires-Dist: argparse
Requires-Dist: keras
Requires-Dist: pathlib
Requires-Dist: matplotlib
Requires-Dist: scikit-image
Requires-Dist: dlib
Requires-Dist: Theano
